build/lib/build/lib/coininfo_vincent/__init__.py
build/lib/build/lib/coininfo_vincent/info.py
build/lib/build/lib/env/bin/rst2html.py
build/lib/build/lib/env/bin/rst2html4.py
build/lib/build/lib/env/bin/rst2html5.py
build/lib/build/lib/env/bin/rst2latex.py
build/lib/build/lib/env/bin/rst2man.py
build/lib/build/lib/env/bin/rst2odt.py
build/lib/build/lib/env/bin/rst2odt_prepstyles.py
build/lib/build/lib/env/bin/rst2pseudoxml.py
build/lib/build/lib/env/bin/rst2s5.py
build/lib/build/lib/env/bin/rst2xetex.py
build/lib/build/lib/env/bin/rst2xml.py
build/lib/build/lib/env/bin/rstpep2html.py
build/lib/coininfo_vincent/__init__.py
build/lib/coininfo_vincent/info.py
build/lib/env/bin/rst2html.py
build/lib/env/bin/rst2html4.py
build/lib/env/bin/rst2html5.py
build/lib/env/bin/rst2latex.py
build/lib/env/bin/rst2man.py
build/lib/env/bin/rst2odt.py
build/lib/env/bin/rst2odt_prepstyles.py
build/lib/env/bin/rst2pseudoxml.py
build/lib/env/bin/rst2s5.py
build/lib/env/bin/rst2xetex.py
build/lib/env/bin/rst2xml.py
build/lib/env/bin/rstpep2html.py
coininfo_vincent/__init__.py
coininfo_vincent/info.py
env/bin/rst2html.py
env/bin/rst2html4.py
env/bin/rst2html5.py
env/bin/rst2latex.py
env/bin/rst2man.py
env/bin/rst2odt.py
env/bin/rst2odt_prepstyles.py
env/bin/rst2pseudoxml.py
env/bin/rst2s5.py
env/bin/rst2xetex.py
env/bin/rst2xml.py
env/bin/rstpep2html.py
coininfo_vincent-0.1.1.dist-info/METADATA
coininfo_vincent-0.1.1.dist-info/WHEEL
coininfo_vincent-0.1.1.dist-info/top_level.txt
coininfo_vincent-0.1.1.dist-info/RECORD
